{
  "token_url": "http://gnrd.globalnames.org/name_finder.json?token=O5LExLcrRj241Yq1SUIosQ",
  "input_url": null,
  "file": "Embryology 1988_ 113.tiff",
  "status": 200,
  "engines": [
    "TaxonFinder",
    "NetiNeti"
  ],
  "unique": false,
  "verbatim": true,
  "english": true,
  "execution_time": {
    "find_names_duration": 0.104561694,
    "resolve_names_duration": 0.78477842,
    "total_duration": 23.83579991
  },
  "agent": "",
  "created": "2013-06-18T13:05:58-04:00",
  "total": 1,
  "names": [
    {
      "verbatim": "Fundulus",
      "scientificName": "Fundulus",
      "offsetStart": 884,
      "offsetEnd": 891,
      "identifiedName": "Fundulus"
    }
  ],
  "content": "Tuesday, Jul! 19\nEmbryology Course\nModule IV\nGene Control of Spatial Differentiation in the Embryo\n10:00 AM Eric Wleschaus Lecture\nPM E. Wieschaus Lab\n20\n10:00 AM E. Wieschaus Lecture\nPM E. Wieschaus Lab\nThursday, July 21\n11:00 AM Douglas Melton (Harvard) Lecture\nPM E. Wischaus Lab\nFriday, Jul! 22\nAM E. Wieschaus Lab\n1:30 PM Lionel Jaffe Lecture\nPM L. Jaffe Lab\nsgiurdal, July 23 \n10:00 AM Richard Whittaker Lecture\nPM R. Pranks Lab\nSunday, July 24\nPM R. Franks Lab\nMonday, July 25\n10:00 AM John Trinkaus Lecture\nPM L. Jaffe Lab\nPM fl. Trinkaus Lab\n\"Genetic insight into\ndevelopment\"\n\"Segmentation\"\n\"The role of localized\nand horneobox\ngene products in early frog\ndevelopment\"\n\"vibrating probe\"\n\"Differentiation of\nascidian pigment cells\"\nInjection of see urchin\neggs--1/2 of class\nInjection of sea urchin\neggs--1/2 of class\n\"Directional movements of\npigment Cells in fish\nembryos\"\nFundulus demonstration\n\n",
  "data_sources": [

  ],
  "context": null,
  "resolved_names": [
    {
      "supplied_name_string": "Fundulus",
      "results": [
        {
          "data_source_id": 1,
          "data_source_title": "Catalogue of Life",
          "gni_uuid": "849efb3e-564d-5bed-b388-d2abd1e89de0",
          "name_string": "Fundulus",
          "canonical_form": "Fundulus",
          "classification_path": "Animalia|Chordata|Actinopterygii|Cyprinodontiformes|Fundulidae|Fundulus",
          "classification_path_ranks": "kingdom|phylum|class|order|family|genus",
          "classification_path_ids": "2362377|2362754|2365430|2369356|2369363|2396458",
          "taxon_id": "2396458",
          "match_type": 1,
          "prescore": "1|0|0",
          "score": 0.75
        }
      ],
      "preferred_results": [
        {
          "data_source_id": 12,
          "data_source_title": "EOL",
          "gni_uuid": "849efb3e-564d-5bed-b388-d2abd1e89de0",
          "name_string": "Fundulus",
          "canonical_form": "Fundulus",
          "classification_path": "",
          "classification_path_ranks": "",
          "classification_path_ids": "",
          "taxon_id": "37305680",
          "local_id": "207614",
          "url": "http://eol.org/pages/207614",
          "match_type": 1,
          "prescore": "1|0|0",
          "score": 0.75
        }
      ],
      "data_sources_number": 16,
      "in_curated_sources": true
    }
  ]
}